LICENSE.txt
setup.py
kivygo/__init__.py
kivygo/animation.py
kivygo/app.py
kivygo/bounds_math.py
kivygo/colors.py
kivygo/palette.py
kivygo/transformations.py
kivygo/utils.py
kivygo.egg-info/PKG-INFO
kivygo.egg-info/SOURCES.txt
kivygo.egg-info/dependency_links.txt
kivygo.egg-info/requires.txt
kivygo.egg-info/top_level.txt
kivygo/behaviors/__init__.py
kivygo/behaviors/button.py
kivygo/behaviors/drag_and_drop.py
kivygo/behaviors/effect.py
kivygo/behaviors/hover.py
kivygo/behaviors/neumorph.py
kivygo/behaviors/resizable.py
kivygo/behaviors/thumb.py
kivygo/config/coins.atlas
kivygo/config/coins.bounds
kivygo/config/drugs.pex
kivygo/config/fire.pex
kivygo/config/jellyfish.pex
kivygo/config/particle.pex
kivygo/config/particle.png
kivygo/config/sun.pex
kivygo/elevation/elevation.frag
kivygo/elevation/header.frag
kivygo/elevation/main.frag
kivygo/icons/bg_example.png
kivygo/icons/coins.png
kivygo/icons/discord.svg
kivygo/icons/discord2.svg
kivygo/icons/facebook2.svg
kivygo/icons/github.svg
kivygo/icons/github2.svg
kivygo/icons/github3.svg
kivygo/icons/google.svg
kivygo/icons/google3.svg
kivygo/icons/kivy.png
kivygo/icons/kivy.svg
kivygo/icons/kivy_logo.png
kivygo/icons/kivymd_logo.png
kivygo/icons/pie_chart.svg
kivygo/icons/pipette.png
kivygo/icons/python2.svg
kivygo/icons/search.svg
kivygo/icons/so.svg
kivygo/icons/square.png
kivygo/icons/sublime.svg
kivygo/icons/text.svg
kivygo/icons/transparent.png
kivygo/icons/twitter2.svg
kivygo/images/6915-green.png
kivygo/images/Path.png
kivygo/images/busan.jpg
kivygo/images/demoimage.jpg
kivygo/images/icon-kivygo.png
kivygo/images/iris.jpg
kivygo/images/lion.jpg
kivygo/images/navigationdrawer_gradient_ltor.png
kivygo/images/navigationdrawer_gradient_rtol.png
kivygo/images/test.jpg
kivygo/layouts/__init__.py
kivygo/layouts/anchorlayout.py
kivygo/layouts/boxlayout.py
kivygo/layouts/circularlayout.py
kivygo/layouts/floatlayout.py
kivygo/layouts/gridlayout.py
kivygo/transitions/Angular.glsl
kivygo/transitions/Bounce.glsl
kivygo/transitions/BowTieHorizontal.glsl
kivygo/transitions/BowTieVertical.glsl
kivygo/transitions/Burn.glsl
kivygo/transitions/ButterflyWaveScrawler.glsl
