Metadata-Version: 2.1
Name: kivygo
Version: 0.1.0
Requires-Python: >=3.7
License-File: LICENSE.txt
Requires-Dist: kivy>=2.0.0
Requires-Dist: pillow
Requires-Dist: opencv-python
Requires-Dist: camera4kivy
Requires-Dist: matplotlib
Requires-Dist: pyzbar
Requires-Dist: future
Requires-Dist: requests
Requires-Dist: svglib
Requires-Dist: svg.path
